dsto_gan/__init__.py
dsto_gan/dsto_gan.py
dsto_gan-0.1.9.dist-info/LICENCE
dsto_gan-0.1.9.dist-info/METADATA
dsto_gan-0.1.9.dist-info/WHEEL
dsto_gan-0.1.9.dist-info/top_level.txt
dsto_gan-0.1.9.dist-info/RECORD
