Metadata-Version: 2.1
Name: dsto-gan
Version: 0.1.9
Summary: Library for balancing tabular data with Deep SMOTE Optimize.
Home-page: https://github.com/erikaduda/dsto_gan
Author: Erika Assis
Author-email: dudabh@gmail.com
Keywords: deep smote tabular optimize gan
Classifier: Programming Language :: Python :: 3
Classifier: Programming Language :: Python :: 3.7
Classifier: Programming Language :: Python :: 3.8
Classifier: Programming Language :: Python :: 3.9
Classifier: Programming Language :: Python :: 3.10
Classifier: License :: OSI Approved :: MIT License
Classifier: Operating System :: OS Independent
Classifier: Development Status :: 3 - Alpha
Classifier: Intended Audience :: Science/Research
Classifier: Topic :: Scientific/Engineering :: Artificial Intelligence
Requires-Python: >=3.7
License-File: LICENCE
Requires-Dist: numpy
Requires-Dist: torch>=1.10.0
Requires-Dist: pandas>=1.3.0
Requires-Dist: scikit-learn>=1.0.0
Requires-Dist: xgboost>=1.5.0
Requires-Dist: scikit-optimize>=0.9.0
Provides-Extra: dev
Requires-Dist: pytest>=6.0; extra == "dev"
Requires-Dist: black>=22.0; extra == "dev"
Requires-Dist: flake8>=4.0; extra == "dev"
